ordered_rectangles/__init__.py
ordered_rectangles/extra.py
ordered_rectangles/main.py
ordered_rectangles-0.0.6.dist-info/METADATA
ordered_rectangles-0.0.6.dist-info/WHEEL
ordered_rectangles-0.0.6.dist-info/top_level.txt
ordered_rectangles-0.0.6.dist-info/RECORD
