Metadata-Version: 2.1
Name: ordered-rectangles
Version: 0.0.6
Summary: Environment to python dictionary parser util
Home-page: https://github.com/PasaOpasen/rectangles-text-view-util
Author: Demetry Pascal
Author-email: qtckpuhdsa@gmail.com
Maintainer: Demetry Pascal
License: MIT
Keywords: rectangles
Classifier: Programming Language :: Python :: 3.8
Classifier: License :: OSI Approved :: MIT License
Classifier: Operating System :: OS Independent
Classifier: Topic :: Software Development :: Libraries :: Python Modules
Requires-Dist: typing-extensions
Requires-Dist: numpy
Provides-Extra: extra
Requires-Dist: reportlab ; extra == 'extra'
